auditry/__init__.py
auditry/correlation.py
auditry/logging_config.py
auditry/models.py
auditry/path_matcher.py
auditry/py.typed
auditry/redaction.py
auditry/core/__init__.py
auditry/core/base.py
auditry/core/logger.py
auditry/fastapi/__init__.py
auditry/fastapi/adapters.py
auditry/fastapi/middleware.py
auditry/quart/__init__.py
auditry/quart/adapters.py
auditry/quart/middleware.py
auditry-0.2.6.dist-info/LICENSE
auditry-0.2.6.dist-info/METADATA
auditry-0.2.6.dist-info/WHEEL
auditry-0.2.6.dist-info/top_level.txt
auditry-0.2.6.dist-info/RECORD
