Metadata-Version: 2.1
Name: auditry
Version: 0.2.6
Summary: Observability middleware for FastAPI and Quart with request/response logging, correlation IDs, and sensitive data redaction
Author-email: Liv Stark <livstark.work@gmail.com>
License: MIT
Project-URL: Homepage, https://github.com/lst4rk/auditry
Project-URL: Repository, https://github.com/lst4rk/auditry
Project-URL: Issues, https://github.com/lst4rk/auditry/issues
Keywords: fastapi,quart,observability,logging,middleware,correlation-id,redaction
Classifier: Development Status :: 4 - Beta
Classifier: Intended Audience :: Developers
Classifier: Programming Language :: Python :: 3
Classifier: Programming Language :: Python :: 3.9
Classifier: Programming Language :: Python :: 3.10
Classifier: Programming Language :: Python :: 3.11
Classifier: Programming Language :: Python :: 3.12
Classifier: Framework :: FastAPI
Classifier: Framework :: AsyncIO
Classifier: Topic :: Software Development :: Libraries :: Python Modules
Classifier: Topic :: System :: Logging
Requires-Python: >=3.9
License-File: LICENSE
Requires-Dist: pydantic>=2.0.0
Requires-Dist: structlog>=23.0.0
Requires-Dist: asgi-correlation-id>=4.0.0
Provides-Extra: all
Requires-Dist: fastapi>=0.100.0; extra == "all"
Requires-Dist: starlette>=0.27.0; extra == "all"
Requires-Dist: quart>=0.18.0; extra == "all"
Provides-Extra: dev
Requires-Dist: pytest>=7.0.0; extra == "dev"
Requires-Dist: pytest-asyncio>=0.21.0; extra == "dev"
Requires-Dist: black>=23.0.0; extra == "dev"
Requires-Dist: mypy>=1.0.0; extra == "dev"
Requires-Dist: ruff>=0.1.0; extra == "dev"
Provides-Extra: fastapi
Requires-Dist: fastapi>=0.100.0; extra == "fastapi"
Requires-Dist: starlette>=0.27.0; extra == "fastapi"
Provides-Extra: quart
Requires-Dist: quart>=0.18.0; extra == "quart"
